pygifconvt_yyummmm/__init__.py
pygifconvt_yyummmm/converter.py
pygifconvt_yyummmm-1.0.2.dist-info/LICENSE
pygifconvt_yyummmm-1.0.2.dist-info/METADATA
pygifconvt_yyummmm-1.0.2.dist-info/WHEEL
pygifconvt_yyummmm-1.0.2.dist-info/top_level.txt
pygifconvt_yyummmm-1.0.2.dist-info/RECORD
